staq/__init__.py
staq/function.py
staq/stack.py
staq/stackDirective.py
staq/stackSession.py
staq/staq_cli.py
staq/archs/__init__.py
staq/archs/architecture.py
staq/archs/arm.py
staq/archs/x86_32.py
staq/data/libc.c
staq/templates/stack-full.html.j2
staq/templates/stack.html.j2
staq/templates/partials/stack-content.html.j2
staq/templates/partials/stack-style.css
staq-0.2.12.dist-info/METADATA
staq-0.2.12.dist-info/WHEEL
staq-0.2.12.dist-info/entry_points.txt
staq-0.2.12.dist-info/RECORD
