Metadata-Version: 2.4
Name: staq
Version: 0.2.12
Summary: Stack Visualization Tool
Project-URL: homepage, https://github.com/username/staq
Project-URL: repository, https://github.com/username/staq
Author-email: Jason Berger <berg472@gmail.com>
License: MIT
Requires-Python: >=3.7
Requires-Dist: ansi2html
Requires-Dist: cliify[prompt-toolkit]
Requires-Dist: html2image
Requires-Dist: jinja2
Requires-Dist: pillow
Requires-Dist: prompt-toolkit
Requires-Dist: pyyaml
Requires-Dist: sphinx
Requires-Dist: termcolor
Provides-Extra: dev
Requires-Dist: pytest>=7.0.0; extra == 'dev'
Requires-Dist: sphinx>=4.0.0; extra == 'dev'
